CHANGELOG.md
ounce/__init__.py
ounce/core.py
ounce-1.1.1.dist-info/LICENSE
ounce-1.1.1.dist-info/WHEEL
ounce-1.1.1.dist-info/METADATA
ounce-1.1.1.dist-info/RECORD
